babyonemoretime/LICENSE
babyonemoretime/README.MD
babyonemoretime/__init__.py
babyonemoretime/requirements.txt
babyonemoretime/thirdparty.json
babyonemoretime-0.10.dist-info/LICENSE.rst
babyonemoretime-0.10.dist-info/METADATA
babyonemoretime-0.10.dist-info/WHEEL
babyonemoretime-0.10.dist-info/top_level.txt
babyonemoretime-0.10.dist-info/RECORD
