Metadata-Version: 2.1
Name: babyonemoretime
Version: 0.10
Summary: Kills python + all subprocesses, restarts with the same args, Windows only, works with pyinstaller
Home-page: https://github.com/hansalemaos/babyonemoretime
Author: Johannes Fischer
Author-email: <aulasparticularesdealemaosp@gmail.com>
License: MIT
Keywords: restart,python,execl,osexecl
Classifier: Development Status :: 4 - Beta
Classifier: Programming Language :: Python :: 3 :: Only
Classifier: Programming Language :: Python :: 3.9
Classifier: Topic :: Scientific/Engineering :: Visualization
Classifier: Topic :: Software Development :: Libraries :: Python Modules
Classifier: Topic :: Text Editors :: Text Processing
Classifier: Topic :: Text Processing :: General
Classifier: Topic :: Text Processing :: Indexing
Classifier: Topic :: Text Processing :: Filters
Classifier: Topic :: Utilities
License-File: LICENSE.rst
Requires-Dist: mainprocess
Requires-Dist: psutil
Requires-Dist: touchtouch
